e23data/__init__.py
e23data/client.py
e23data-0.1.0.dist-info/LICENCE
e23data-0.1.0.dist-info/METADATA
e23data-0.1.0.dist-info/WHEEL
e23data-0.1.0.dist-info/top_level.txt
e23data-0.1.0.dist-info/RECORD
