Metadata-Version: 2.1
Name: e23data
Version: 0.1.0
Summary: A Python client library for the E23Data Chemical Properties API.
Author-email: Eduardo Capella <edufeq03@gmail.com>
Project-URL: Homepage, https://github.com/edufeq03/e23data-py
Project-URL: Bug Tracker, https://github.com/edufeq03/e23data-py/issues
Classifier: Programming Language :: Python :: 3
Classifier: License :: OSI Approved :: MIT License
Classifier: Operating System :: OS Independent
Classifier: Topic :: Scientific/Engineering :: Chemistry
Classifier: Topic :: Scientific/Engineering :: Physics
Classifier: Topic :: Software Development :: Libraries :: Python Modules
Requires-Python: >=3.8
License-File: LICENCE
Requires-Dist: requests
